{
  "latest": {
    "filename": "servers.csv",
    "url": "https://raw.githubusercontent.com/funcra/vg-mirror/main/servers.csv",
    "description": "Most recent VPN Gate servers data",
    "is_latest": true
  },
  "historical": [
    {
      "filename": "servers-20260218-1101.csv",
      "url": "https://raw.githubusercontent.com/funcra/vg-mirror/main/servers_history/servers-20260218-1101.csv",
      "description": "VPN Gate servers data from 2026-02-18 11:01 JST",
      "datetime": "20260218-1101",
      "formatted_datetime": "2026-02-18 11:01 JST"
    },
    {
      "filename": "servers-20260218-0729.csv",
      "url": "https://raw.githubusercontent.com/funcra/vg-mirror/main/servers_history/servers-20260218-0729.csv",
      "description": "VPN Gate servers data from 2026-02-18 07:29 JST",
      "datetime": "20260218-0729",
      "formatted_datetime": "2026-02-18 07:29 JST"
    },
    {
      "filename": "servers-20260218-0534.csv",
      "url": "https://raw.githubusercontent.com/funcra/vg-mirror/main/servers_history/servers-20260218-0534.csv",
      "description": "VPN Gate servers data from 2026-02-18 05:34 JST",
      "datetime": "20260218-0534",
      "formatted_datetime": "2026-02-18 05:34 JST"
    },
    {
      "filename": "servers-20260218-0355.csv",
      "url": "https://raw.githubusercontent.com/funcra/vg-mirror/main/servers_history/servers-20260218-0355.csv",
      "description": "VPN Gate servers data from 2026-02-18 03:55 JST",
      "datetime": "20260218-0355",
      "formatted_datetime": "2026-02-18 03:55 JST"
    },
    {
      "filename": "servers-20260218-0155.csv",
      "url": "https://raw.githubusercontent.com/funcra/vg-mirror/main/servers_history/servers-20260218-0155.csv",
      "description": "VPN Gate servers data from 2026-02-18 01:55 JST",
      "datetime": "20260218-0155",
      "formatted_datetime": "2026-02-18 01:55 JST"
    },
    {
      "filename": "servers-20260217-2342.csv",
      "url": "https://raw.githubusercontent.com/funcra/vg-mirror/main/servers_history/servers-20260217-2342.csv",
      "description": "VPN Gate servers data from 2026-02-17 23:42 JST",
      "datetime": "20260217-2342",
      "formatted_datetime": "2026-02-17 23:42 JST"
    },
    {
      "filename": "servers-20260217-2159.csv",
      "url": "https://raw.githubusercontent.com/funcra/vg-mirror/main/servers_history/servers-20260217-2159.csv",
      "description": "VPN Gate servers data from 2026-02-17 21:59 JST",
      "datetime": "20260217-2159",
      "formatted_datetime": "2026-02-17 21:59 JST"
    },
    {
      "filename": "servers-20260217-1942.csv",
      "url": "https://raw.githubusercontent.com/funcra/vg-mirror/main/servers_history/servers-20260217-1942.csv",
      "description": "VPN Gate servers data from 2026-02-17 19:42 JST",
      "datetime": "20260217-1942",
      "formatted_datetime": "2026-02-17 19:42 JST"
    },
    {
      "filename": "servers-20260217-1742.csv",
      "url": "https://raw.githubusercontent.com/funcra/vg-mirror/main/servers_history/servers-20260217-1742.csv",
      "description": "VPN Gate servers data from 2026-02-17 17:42 JST",
      "datetime": "20260217-1742",
      "formatted_datetime": "2026-02-17 17:42 JST"
    }
  ],
  "total_files": 10,
  "update_frequency": "Every 2 hours",
  "timezone": "JST (UTC+9)",
  "max_history": 10,
  "generated_at": "2026-02-18T02:01:15.605310",
  "usage": {
    "latest_download": "curl -O https://raw.githubusercontent.com/funcra/vg-mirror/main/servers.csv",
    "historical_download": "curl -O https://raw.githubusercontent.com/funcra/vg-mirror/main/servers_history/servers-YYYYMMDD-HHMM.csv",
    "note": "Replace YYYYMMDD-HHMM with actual datetime from available files"
  }
}