{
  "latest": {
    "filename": "servers.csv",
    "url": "https://raw.githubusercontent.com/funcra/vg-mirror/main/servers.csv",
    "description": "Most recent VPN Gate servers data",
    "is_latest": true
  },
  "historical": [
    {
      "filename": "servers-20260628-0759.csv",
      "url": "https://raw.githubusercontent.com/funcra/vg-mirror/main/servers_history/servers-20260628-0759.csv",
      "description": "VPN Gate servers data from 2026-06-28 07:59 JST",
      "datetime": "20260628-0759",
      "formatted_datetime": "2026-06-28 07:59 JST"
    },
    {
      "filename": "servers-20260628-0600.csv",
      "url": "https://raw.githubusercontent.com/funcra/vg-mirror/main/servers_history/servers-20260628-0600.csv",
      "description": "VPN Gate servers data from 2026-06-28 06:00 JST",
      "datetime": "20260628-0600",
      "formatted_datetime": "2026-06-28 06:00 JST"
    },
    {
      "filename": "servers-20260628-0416.csv",
      "url": "https://raw.githubusercontent.com/funcra/vg-mirror/main/servers_history/servers-20260628-0416.csv",
      "description": "VPN Gate servers data from 2026-06-28 04:16 JST",
      "datetime": "20260628-0416",
      "formatted_datetime": "2026-06-28 04:16 JST"
    },
    {
      "filename": "servers-20260628-0206.csv",
      "url": "https://raw.githubusercontent.com/funcra/vg-mirror/main/servers_history/servers-20260628-0206.csv",
      "description": "VPN Gate servers data from 2026-06-28 02:06 JST",
      "datetime": "20260628-0206",
      "formatted_datetime": "2026-06-28 02:06 JST"
    },
    {
      "filename": "servers-20260628-0013.csv",
      "url": "https://raw.githubusercontent.com/funcra/vg-mirror/main/servers_history/servers-20260628-0013.csv",
      "description": "VPN Gate servers data from 2026-06-28 00:13 JST",
      "datetime": "20260628-0013",
      "formatted_datetime": "2026-06-28 00:13 JST"
    },
    {
      "filename": "servers-20260627-2227.csv",
      "url": "https://raw.githubusercontent.com/funcra/vg-mirror/main/servers_history/servers-20260627-2227.csv",
      "description": "VPN Gate servers data from 2026-06-27 22:27 JST",
      "datetime": "20260627-2227",
      "formatted_datetime": "2026-06-27 22:27 JST"
    },
    {
      "filename": "servers-20260627-1905.csv",
      "url": "https://raw.githubusercontent.com/funcra/vg-mirror/main/servers_history/servers-20260627-1905.csv",
      "description": "VPN Gate servers data from 2026-06-27 19:05 JST",
      "datetime": "20260627-1905",
      "formatted_datetime": "2026-06-27 19:05 JST"
    },
    {
      "filename": "servers-20260627-1550.csv",
      "url": "https://raw.githubusercontent.com/funcra/vg-mirror/main/servers_history/servers-20260627-1550.csv",
      "description": "VPN Gate servers data from 2026-06-27 15:50 JST",
      "datetime": "20260627-1550",
      "formatted_datetime": "2026-06-27 15:50 JST"
    },
    {
      "filename": "servers-20260627-1153.csv",
      "url": "https://raw.githubusercontent.com/funcra/vg-mirror/main/servers_history/servers-20260627-1153.csv",
      "description": "VPN Gate servers data from 2026-06-27 11:53 JST",
      "datetime": "20260627-1153",
      "formatted_datetime": "2026-06-27 11:53 JST"
    }
  ],
  "total_files": 10,
  "update_frequency": "Every 2 hours",
  "timezone": "JST (UTC+9)",
  "max_history": 10,
  "generated_at": "2026-06-27T22:59:30.617126",
  "usage": {
    "latest_download": "curl -O https://raw.githubusercontent.com/funcra/vg-mirror/main/servers.csv",
    "historical_download": "curl -O https://raw.githubusercontent.com/funcra/vg-mirror/main/servers_history/servers-YYYYMMDD-HHMM.csv",
    "note": "Replace YYYYMMDD-HHMM with actual datetime from available files"
  }
}