{
  "latest": {
    "filename": "servers.csv",
    "url": "https://raw.githubusercontent.com/funcra/vg-mirror/main/servers.csv",
    "description": "Most recent VPN Gate servers data",
    "is_latest": true
  },
  "historical": [
    {
      "filename": "servers-20250925-1340.csv",
      "url": "https://raw.githubusercontent.com/funcra/vg-mirror/main/servers_history/servers-20250925-1340.csv",
      "description": "VPN Gate servers data from 2025-09-25 13:40 JST",
      "datetime": "20250925-1340",
      "formatted_datetime": "2025-09-25 13:40 JST"
    },
    {
      "filename": "servers-20250925-1211.csv",
      "url": "https://raw.githubusercontent.com/funcra/vg-mirror/main/servers_history/servers-20250925-1211.csv",
      "description": "VPN Gate servers data from 2025-09-25 12:11 JST",
      "datetime": "20250925-1211",
      "formatted_datetime": "2025-09-25 12:11 JST"
    },
    {
      "filename": "servers-20250925-0732.csv",
      "url": "https://raw.githubusercontent.com/funcra/vg-mirror/main/servers_history/servers-20250925-0732.csv",
      "description": "VPN Gate servers data from 2025-09-25 07:32 JST",
      "datetime": "20250925-0732",
      "formatted_datetime": "2025-09-25 07:32 JST"
    },
    {
      "filename": "servers-20250925-0533.csv",
      "url": "https://raw.githubusercontent.com/funcra/vg-mirror/main/servers_history/servers-20250925-0533.csv",
      "description": "VPN Gate servers data from 2025-09-25 05:33 JST",
      "datetime": "20250925-0533",
      "formatted_datetime": "2025-09-25 05:33 JST"
    },
    {
      "filename": "servers-20250925-0344.csv",
      "url": "https://raw.githubusercontent.com/funcra/vg-mirror/main/servers_history/servers-20250925-0344.csv",
      "description": "VPN Gate servers data from 2025-09-25 03:44 JST",
      "datetime": "20250925-0344",
      "formatted_datetime": "2025-09-25 03:44 JST"
    },
    {
      "filename": "servers-20250925-0147.csv",
      "url": "https://raw.githubusercontent.com/funcra/vg-mirror/main/servers_history/servers-20250925-0147.csv",
      "description": "VPN Gate servers data from 2025-09-25 01:47 JST",
      "datetime": "20250925-0147",
      "formatted_datetime": "2025-09-25 01:47 JST"
    },
    {
      "filename": "servers-20250924-2338.csv",
      "url": "https://raw.githubusercontent.com/funcra/vg-mirror/main/servers_history/servers-20250924-2338.csv",
      "description": "VPN Gate servers data from 2025-09-24 23:38 JST",
      "datetime": "20250924-2338",
      "formatted_datetime": "2025-09-24 23:38 JST"
    },
    {
      "filename": "servers-20250924-2234.csv",
      "url": "https://raw.githubusercontent.com/funcra/vg-mirror/main/servers_history/servers-20250924-2234.csv",
      "description": "VPN Gate servers data from 2025-09-24 22:34 JST",
      "datetime": "20250924-2234",
      "formatted_datetime": "2025-09-24 22:34 JST"
    },
    {
      "filename": "servers-20250924-1939.csv",
      "url": "https://raw.githubusercontent.com/funcra/vg-mirror/main/servers_history/servers-20250924-1939.csv",
      "description": "VPN Gate servers data from 2025-09-24 19:39 JST",
      "datetime": "20250924-1939",
      "formatted_datetime": "2025-09-24 19:39 JST"
    }
  ],
  "total_files": 10,
  "update_frequency": "Every 2 hours",
  "timezone": "JST (UTC+9)",
  "max_history": 10,
  "generated_at": "2025-09-25T04:40:19.777018",
  "usage": {
    "latest_download": "curl -O https://raw.githubusercontent.com/funcra/vg-mirror/main/servers.csv",
    "historical_download": "curl -O https://raw.githubusercontent.com/funcra/vg-mirror/main/servers_history/servers-YYYYMMDD-HHMM.csv",
    "note": "Replace YYYYMMDD-HHMM with actual datetime from available files"
  }
}