{
  "latest": {
    "filename": "servers.csv",
    "url": "https://raw.githubusercontent.com/funcra/vg-mirror/main/servers.csv",
    "description": "Most recent VPN Gate servers data",
    "is_latest": true
  },
  "historical": [
    {
      "filename": "servers-20260327-1603.csv",
      "url": "https://raw.githubusercontent.com/funcra/vg-mirror/main/servers_history/servers-20260327-1603.csv",
      "description": "VPN Gate servers data from 2026-03-27 16:03 JST",
      "datetime": "20260327-1603",
      "formatted_datetime": "2026-03-27 16:03 JST"
    },
    {
      "filename": "servers-20260327-1441.csv",
      "url": "https://raw.githubusercontent.com/funcra/vg-mirror/main/servers_history/servers-20260327-1441.csv",
      "description": "VPN Gate servers data from 2026-03-27 14:41 JST",
      "datetime": "20260327-1441",
      "formatted_datetime": "2026-03-27 14:41 JST"
    },
    {
      "filename": "servers-20260327-1108.csv",
      "url": "https://raw.githubusercontent.com/funcra/vg-mirror/main/servers_history/servers-20260327-1108.csv",
      "description": "VPN Gate servers data from 2026-03-27 11:08 JST",
      "datetime": "20260327-1108",
      "formatted_datetime": "2026-03-27 11:08 JST"
    },
    {
      "filename": "servers-20260327-0727.csv",
      "url": "https://raw.githubusercontent.com/funcra/vg-mirror/main/servers_history/servers-20260327-0727.csv",
      "description": "VPN Gate servers data from 2026-03-27 07:27 JST",
      "datetime": "20260327-0727",
      "formatted_datetime": "2026-03-27 07:27 JST"
    },
    {
      "filename": "servers-20260327-0533.csv",
      "url": "https://raw.githubusercontent.com/funcra/vg-mirror/main/servers_history/servers-20260327-0533.csv",
      "description": "VPN Gate servers data from 2026-03-27 05:33 JST",
      "datetime": "20260327-0533",
      "formatted_datetime": "2026-03-27 05:33 JST"
    },
    {
      "filename": "servers-20260327-0402.csv",
      "url": "https://raw.githubusercontent.com/funcra/vg-mirror/main/servers_history/servers-20260327-0402.csv",
      "description": "VPN Gate servers data from 2026-03-27 04:02 JST",
      "datetime": "20260327-0402",
      "formatted_datetime": "2026-03-27 04:02 JST"
    },
    {
      "filename": "servers-20260327-0158.csv",
      "url": "https://raw.githubusercontent.com/funcra/vg-mirror/main/servers_history/servers-20260327-0158.csv",
      "description": "VPN Gate servers data from 2026-03-27 01:58 JST",
      "datetime": "20260327-0158",
      "formatted_datetime": "2026-03-27 01:58 JST"
    },
    {
      "filename": "servers-20260327-0001.csv",
      "url": "https://raw.githubusercontent.com/funcra/vg-mirror/main/servers_history/servers-20260327-0001.csv",
      "description": "VPN Gate servers data from 2026-03-27 00:01 JST",
      "datetime": "20260327-0001",
      "formatted_datetime": "2026-03-27 00:01 JST"
    },
    {
      "filename": "servers-20260326-2210.csv",
      "url": "https://raw.githubusercontent.com/funcra/vg-mirror/main/servers_history/servers-20260326-2210.csv",
      "description": "VPN Gate servers data from 2026-03-26 22:10 JST",
      "datetime": "20260326-2210",
      "formatted_datetime": "2026-03-26 22:10 JST"
    }
  ],
  "total_files": 10,
  "update_frequency": "Every 2 hours",
  "timezone": "JST (UTC+9)",
  "max_history": 10,
  "generated_at": "2026-03-27T07:03:47.313773",
  "usage": {
    "latest_download": "curl -O https://raw.githubusercontent.com/funcra/vg-mirror/main/servers.csv",
    "historical_download": "curl -O https://raw.githubusercontent.com/funcra/vg-mirror/main/servers_history/servers-YYYYMMDD-HHMM.csv",
    "note": "Replace YYYYMMDD-HHMM with actual datetime from available files"
  }
}