{
  "latest": {
    "filename": "servers.csv",
    "url": "https://raw.githubusercontent.com/funcra/vg-mirror/main/servers.csv",
    "description": "Most recent VPN Gate servers data",
    "is_latest": true
  },
  "historical": [
    {
      "filename": "servers-20260718-0746.csv",
      "url": "https://raw.githubusercontent.com/funcra/vg-mirror/main/servers_history/servers-20260718-0746.csv",
      "description": "VPN Gate servers data from 2026-07-18 07:46 JST",
      "datetime": "20260718-0746",
      "formatted_datetime": "2026-07-18 07:46 JST"
    },
    {
      "filename": "servers-20260718-0551.csv",
      "url": "https://raw.githubusercontent.com/funcra/vg-mirror/main/servers_history/servers-20260718-0551.csv",
      "description": "VPN Gate servers data from 2026-07-18 05:51 JST",
      "datetime": "20260718-0551",
      "formatted_datetime": "2026-07-18 05:51 JST"
    },
    {
      "filename": "servers-20260718-0403.csv",
      "url": "https://raw.githubusercontent.com/funcra/vg-mirror/main/servers_history/servers-20260718-0403.csv",
      "description": "VPN Gate servers data from 2026-07-18 04:03 JST",
      "datetime": "20260718-0403",
      "formatted_datetime": "2026-07-18 04:03 JST"
    },
    {
      "filename": "servers-20260718-0208.csv",
      "url": "https://raw.githubusercontent.com/funcra/vg-mirror/main/servers_history/servers-20260718-0208.csv",
      "description": "VPN Gate servers data from 2026-07-18 02:08 JST",
      "datetime": "20260718-0208",
      "formatted_datetime": "2026-07-18 02:08 JST"
    },
    {
      "filename": "servers-20260718-0010.csv",
      "url": "https://raw.githubusercontent.com/funcra/vg-mirror/main/servers_history/servers-20260718-0010.csv",
      "description": "VPN Gate servers data from 2026-07-18 00:10 JST",
      "datetime": "20260718-0010",
      "formatted_datetime": "2026-07-18 00:10 JST"
    },
    {
      "filename": "servers-20260717-2222.csv",
      "url": "https://raw.githubusercontent.com/funcra/vg-mirror/main/servers_history/servers-20260717-2222.csv",
      "description": "VPN Gate servers data from 2026-07-17 22:22 JST",
      "datetime": "20260717-2222",
      "formatted_datetime": "2026-07-17 22:22 JST"
    },
    {
      "filename": "servers-20260717-2019.csv",
      "url": "https://raw.githubusercontent.com/funcra/vg-mirror/main/servers_history/servers-20260717-2019.csv",
      "description": "VPN Gate servers data from 2026-07-17 20:19 JST",
      "datetime": "20260717-2019",
      "formatted_datetime": "2026-07-17 20:19 JST"
    },
    {
      "filename": "servers-20260717-1854.csv",
      "url": "https://raw.githubusercontent.com/funcra/vg-mirror/main/servers_history/servers-20260717-1854.csv",
      "description": "VPN Gate servers data from 2026-07-17 18:54 JST",
      "datetime": "20260717-1854",
      "formatted_datetime": "2026-07-17 18:54 JST"
    },
    {
      "filename": "servers-20260717-1512.csv",
      "url": "https://raw.githubusercontent.com/funcra/vg-mirror/main/servers_history/servers-20260717-1512.csv",
      "description": "VPN Gate servers data from 2026-07-17 15:12 JST",
      "datetime": "20260717-1512",
      "formatted_datetime": "2026-07-17 15:12 JST"
    }
  ],
  "total_files": 10,
  "update_frequency": "Every 2 hours",
  "timezone": "JST (UTC+9)",
  "max_history": 10,
  "generated_at": "2026-07-17T22:46:23.882413",
  "usage": {
    "latest_download": "curl -O https://raw.githubusercontent.com/funcra/vg-mirror/main/servers.csv",
    "historical_download": "curl -O https://raw.githubusercontent.com/funcra/vg-mirror/main/servers_history/servers-YYYYMMDD-HHMM.csv",
    "note": "Replace YYYYMMDD-HHMM with actual datetime from available files"
  }
}