{
  "latest": {
    "filename": "servers.csv",
    "url": "https://raw.githubusercontent.com/funcra/vg-mirror/main/servers.csv",
    "description": "Most recent VPN Gate servers data",
    "is_latest": true
  },
  "historical": [
    {
      "filename": "servers-20260405-0726.csv",
      "url": "https://raw.githubusercontent.com/funcra/vg-mirror/main/servers_history/servers-20260405-0726.csv",
      "description": "VPN Gate servers data from 2026-04-05 07:26 JST",
      "datetime": "20260405-0726",
      "formatted_datetime": "2026-04-05 07:26 JST"
    },
    {
      "filename": "servers-20260405-0528.csv",
      "url": "https://raw.githubusercontent.com/funcra/vg-mirror/main/servers_history/servers-20260405-0528.csv",
      "description": "VPN Gate servers data from 2026-04-05 05:28 JST",
      "datetime": "20260405-0528",
      "formatted_datetime": "2026-04-05 05:28 JST"
    },
    {
      "filename": "servers-20260405-0339.csv",
      "url": "https://raw.githubusercontent.com/funcra/vg-mirror/main/servers_history/servers-20260405-0339.csv",
      "description": "VPN Gate servers data from 2026-04-05 03:39 JST",
      "datetime": "20260405-0339",
      "formatted_datetime": "2026-04-05 03:39 JST"
    },
    {
      "filename": "servers-20260405-0133.csv",
      "url": "https://raw.githubusercontent.com/funcra/vg-mirror/main/servers_history/servers-20260405-0133.csv",
      "description": "VPN Gate servers data from 2026-04-05 01:33 JST",
      "datetime": "20260405-0133",
      "formatted_datetime": "2026-04-05 01:33 JST"
    },
    {
      "filename": "servers-20260404-2331.csv",
      "url": "https://raw.githubusercontent.com/funcra/vg-mirror/main/servers_history/servers-20260404-2331.csv",
      "description": "VPN Gate servers data from 2026-04-04 23:31 JST",
      "datetime": "20260404-2331",
      "formatted_datetime": "2026-04-04 23:31 JST"
    },
    {
      "filename": "servers-20260404-2151.csv",
      "url": "https://raw.githubusercontent.com/funcra/vg-mirror/main/servers_history/servers-20260404-2151.csv",
      "description": "VPN Gate servers data from 2026-04-04 21:51 JST",
      "datetime": "20260404-2151",
      "formatted_datetime": "2026-04-04 21:51 JST"
    },
    {
      "filename": "servers-20260404-1930.csv",
      "url": "https://raw.githubusercontent.com/funcra/vg-mirror/main/servers_history/servers-20260404-1930.csv",
      "description": "VPN Gate servers data from 2026-04-04 19:30 JST",
      "datetime": "20260404-1930",
      "formatted_datetime": "2026-04-04 19:30 JST"
    },
    {
      "filename": "servers-20260404-1738.csv",
      "url": "https://raw.githubusercontent.com/funcra/vg-mirror/main/servers_history/servers-20260404-1738.csv",
      "description": "VPN Gate servers data from 2026-04-04 17:38 JST",
      "datetime": "20260404-1738",
      "formatted_datetime": "2026-04-04 17:38 JST"
    },
    {
      "filename": "servers-20260404-1558.csv",
      "url": "https://raw.githubusercontent.com/funcra/vg-mirror/main/servers_history/servers-20260404-1558.csv",
      "description": "VPN Gate servers data from 2026-04-04 15:58 JST",
      "datetime": "20260404-1558",
      "formatted_datetime": "2026-04-04 15:58 JST"
    }
  ],
  "total_files": 10,
  "update_frequency": "Every 2 hours",
  "timezone": "JST (UTC+9)",
  "max_history": 10,
  "generated_at": "2026-04-04T22:26:56.262273",
  "usage": {
    "latest_download": "curl -O https://raw.githubusercontent.com/funcra/vg-mirror/main/servers.csv",
    "historical_download": "curl -O https://raw.githubusercontent.com/funcra/vg-mirror/main/servers_history/servers-YYYYMMDD-HHMM.csv",
    "note": "Replace YYYYMMDD-HHMM with actual datetime from available files"
  }
}